{
    "Automata":
        {
            "estados":
            {
             "A":{"valor":[0,0,0,0]},
             "B":{"valor":[0,0,0,1]},
             "C":{"valor":[0,0,0,1]},
             "D":{"valor":[1,0,0,1]},
             "E":{"valor":[0,1,0,0]},
             "F":{"valor":[0,1,1,1]},
             "G":{"valor":[0,0,1,1]},
             "H":{"valor":[1,0,1,1]},
             "I":{"valor":[1,0,1,0]},
             "J":{"valor":[1,1,1,1]},
             "K":{"valor":[0,0,1,0]},
             "L":{"valor":[1,0,1,1]},
             "M":{"valor":[1,0,1,0]}
            },
            "transiciones":
            {

                "A":{},
                "B":{},
                "C":{},
                "D":{},
                "E":{},
                "F":{},
                "G":{},
                "H":{},
                "I":{},
                "J":{},
                "K":{},
                "L":{},
                "M":{}


            },
            "aceptacion":{"estado":[1,1,1,1]},
            "inicial":{"estado": [0,0,0,0]}

        }






}